{"data":[{"nombre":"01 P\u00c1NUCO","total_actas":398,"actas_procesadas":394,"actas_correctas":321,"actas_digitalizadas":373,"actas_acopiadas":398,"total_de_votos":75537,"lista_nominal":193283,"participacion":49.2091,"porcentaje_actas_procesadas":80.6532,"votos_por_partido":[{"partido_imagen":"Pan-Prd.png","votos":10492,"partido_siglas":"Pan Prd","color":"#1081C0","en_grafica":true,"en_tabla":false},{"partido_imagen":"Pri-Pv-Na-Ave-PC.png","votos":8301,"partido_siglas":"Pri Pvem NA AVE Cardenista","color":"#17A151","en_grafica":true,"en_tabla":false},{"partido_imagen":"pt.png","votos":10719,"partido_siglas":"PT","color":"#E93E41","en_grafica":true,"en_tabla":true},{"partido_imagen":"mc.png","votos":11125,"partido_siglas":"MC","color":"#EA622F","en_grafica":true,"en_tabla":true},{"partido_imagen":"mor.png","votos":10865,"partido_siglas":"MOR","color":"#B85756","en_grafica":true,"en_tabla":true},{"partido_imagen":"pes.png","votos":10894,"partido_siglas":"PES","color":"#E84445","en_grafica":true,"en_tabla":true},{"partido_imagen":"juan_bueno.png","votos":10946,"partido_siglas":"JUAN BUENO TORIO","color":"#97AB9F","en_grafica":true,"en_tabla":true},{"partido_imagen":"cnr.png","votos":1117,"partido_siglas":"CNR","color":"#878A87","en_grafica":true,"en_tabla":true},{"partido_imagen":"nulos.png","votos":1078,"partido_siglas":"NULOS","color":"#EEB4BF","en_grafica":true,"en_tabla":true}],"total_votantes":74640,"total_sobrantes":1288,"votos_sacados_urna":1058},{"nombre":"02 TANTOYUCA","total_actas":365,"actas_procesadas":364,"actas_correctas":335,"actas_digitalizadas":364,"actas_acopiadas":365,"total_de_votos":89139,"lista_nominal":191491,"participacion":50.357,"porcentaje_actas_procesadas":91.7808,"votos_por_partido":[{"partido_imagen":"Pan-Prd.png","votos":12978,"partido_siglas":"Pan Prd","color":"#1081C0","en_grafica":true,"en_tabla":false},{"partido_imagen":"Pri-Pv-Na-Ave-PC.png","votos":10239,"partido_siglas":"Pri Pvem NA AVE Cardenista","color":"#17A151","en_grafica":true,"en_tabla":false},{"partido_imagen":"pt.png","votos":12951,"partido_siglas":"PT","color":"#E93E41","en_grafica":true,"en_tabla":true},{"partido_imagen":"mc.png","votos":12952,"partido_siglas":"MC","color":"#EA622F","en_grafica":true,"en_tabla":true},{"partido_imagen":"mor.png","votos":12231,"partido_siglas":"MOR","color":"#B85756","en_grafica":true,"en_tabla":true},{"partido_imagen":"pes.png","votos":12878,"partido_siglas":"PES","color":"#E84445","en_grafica":true,"en_tabla":true},{"partido_imagen":"juan_bueno.png","votos":12429,"partido_siglas":"JUAN BUENO TORIO","color":"#97AB9F","en_grafica":true,"en_tabla":true},{"partido_imagen":"cnr.png","votos":1220,"partido_siglas":"CNR","color":"#878A87","en_grafica":true,"en_tabla":true},{"partido_imagen":"nulos.png","votos":1261,"partido_siglas":"NULOS","color":"#EEB4BF","en_grafica":true,"en_tabla":true}],"total_votantes":81783,"total_sobrantes":1756,"votos_sacados_urna":10025},{"nombre":"03 TUXPAN","total_actas":372,"actas_procesadas":364,"actas_correctas":304,"actas_digitalizadas":363,"actas_acopiadas":367,"total_de_votos":83494,"lista_nominal":205347,"participacion":49.8772,"porcentaje_actas_procesadas":81.7204,"votos_por_partido":[{"partido_imagen":"Pan-Prd.png","votos":11183,"partido_siglas":"Pan Prd","color":"#1081C0","en_grafica":true,"en_tabla":false},{"partido_imagen":"Pri-Pv-Na-Ave-PC.png","votos":9216,"partido_siglas":"Pri Pvem NA AVE Cardenista","color":"#17A151","en_grafica":true,"en_tabla":false},{"partido_imagen":"pt.png","votos":12205,"partido_siglas":"PT","color":"#E93E41","en_grafica":true,"en_tabla":true},{"partido_imagen":"mc.png","votos":12501,"partido_siglas":"MC","color":"#EA622F","en_grafica":true,"en_tabla":true},{"partido_imagen":"mor.png","votos":11787,"partido_siglas":"MOR","color":"#B85756","en_grafica":true,"en_tabla":true},{"partido_imagen":"pes.png","votos":11922,"partido_siglas":"PES","color":"#E84445","en_grafica":true,"en_tabla":true},{"partido_imagen":"juan_bueno.png","votos":12287,"partido_siglas":"JUAN BUENO TORIO","color":"#97AB9F","en_grafica":true,"en_tabla":true},{"partido_imagen":"cnr.png","votos":1206,"partido_siglas":"CNR","color":"#878A87","en_grafica":true,"en_tabla":true},{"partido_imagen":"nulos.png","votos":1187,"partido_siglas":"NULOS","color":"#EEB4BF","en_grafica":true,"en_tabla":true}],"total_votantes":1854,"total_sobrantes":1322,"votos_sacados_urna":84149},{"nombre":"04 \u00c1LAMO TEMAPACHE","total_actas":398,"actas_procesadas":396,"actas_correctas":341,"actas_digitalizadas":372,"actas_acopiadas":398,"total_de_votos":85681,"lista_nominal":201760,"participacion":50.0032,"porcentaje_actas_procesadas":85.6783,"votos_por_partido":[{"partido_imagen":"Pan-Prd.png","votos":11881,"partido_siglas":"Pan Prd","color":"#1081C0","en_grafica":true,"en_tabla":false},{"partido_imagen":"Pri-Pv-Na-Ave-PC.png","votos":9429,"partido_siglas":"Pri Pvem NA AVE Cardenista","color":"#17A151","en_grafica":true,"en_tabla":false},{"partido_imagen":"pt.png","votos":12470,"partido_siglas":"PT","color":"#E93E41","en_grafica":true,"en_tabla":true},{"partido_imagen":"mc.png","votos":12496,"partido_siglas":"MC","color":"#EA622F","en_grafica":true,"en_tabla":true},{"partido_imagen":"mor.png","votos":12049,"partido_siglas":"MOR","color":"#B85756","en_grafica":true,"en_tabla":true},{"partido_imagen":"pes.png","votos":12727,"partido_siglas":"PES","color":"#E84445","en_grafica":true,"en_tabla":true},{"partido_imagen":"juan_bueno.png","votos":12160,"partido_siglas":"JUAN BUENO TORIO","color":"#97AB9F","en_grafica":true,"en_tabla":true},{"partido_imagen":"cnr.png","votos":1251,"partido_siglas":"CNR","color":"#878A87","en_grafica":true,"en_tabla":true},{"partido_imagen":"nulos.png","votos":1218,"partido_siglas":"NULOS","color":"#EEB4BF","en_grafica":true,"en_tabla":true}],"total_votantes":85727,"total_sobrantes":4611,"votos_sacados_urna":2149},{"nombre":"05 POZA RICA","total_actas":323,"actas_procesadas":321,"actas_correctas":296,"actas_digitalizadas":321,"actas_acopiadas":323,"total_de_votos":86678,"lista_nominal":184805,"participacion":50.946,"porcentaje_actas_procesadas":91.6408,"votos_por_partido":[{"partido_imagen":"Pan-Prd.png","votos":12446,"partido_siglas":"Pan Prd","color":"#1081C0","en_grafica":true,"en_tabla":false},{"partido_imagen":"Pri-Pv-Na-Ave-PC.png","votos":9817,"partido_siglas":"Pri Pvem NA AVE Cardenista","color":"#17A151","en_grafica":true,"en_tabla":false},{"partido_imagen":"pt.png","votos":12345,"partido_siglas":"PT","color":"#E93E41","en_grafica":true,"en_tabla":true},{"partido_imagen":"mc.png","votos":12267,"partido_siglas":"MC","color":"#EA622F","en_grafica":true,"en_tabla":true},{"partido_imagen":"mor.png","votos":12850,"partido_siglas":"MOR","color":"#B85756","en_grafica":true,"en_tabla":true},{"partido_imagen":"pes.png","votos":12032,"partido_siglas":"PES","color":"#E84445","en_grafica":true,"en_tabla":true},{"partido_imagen":"juan_bueno.png","votos":12400,"partido_siglas":"JUAN BUENO TORIO","color":"#97AB9F","en_grafica":true,"en_tabla":true},{"partido_imagen":"cnr.png","votos":1352,"partido_siglas":"CNR","color":"#878A87","en_grafica":true,"en_tabla":true},{"partido_imagen":"nulos.png","votos":1169,"partido_siglas":"NULOS","color":"#EEB4BF","en_grafica":true,"en_tabla":true}],"total_votantes":2965,"total_sobrantes":1443,"votos_sacados_urna":87629},{"nombre":"06 PAPANTLA","total_actas":351,"actas_procesadas":348,"actas_correctas":302,"actas_digitalizadas":337,"actas_acopiadas":351,"total_de_votos":89289,"lista_nominal":195530,"participacion":52.8371,"porcentaje_actas_procesadas":86.0398,"votos_por_partido":[{"partido_imagen":"Pan-Prd.png","votos":12485,"partido_siglas":"Pan Prd","color":"#1081C0","en_grafica":true,"en_tabla":false},{"partido_imagen":"Pri-Pv-Na-Ave-PC.png","votos":14167,"partido_siglas":"Pri Pvem NA AVE Cardenista","color":"#17A151","en_grafica":true,"en_tabla":false},{"partido_imagen":"pt.png","votos":11662,"partido_siglas":"PT","color":"#E93E41","en_grafica":true,"en_tabla":true},{"partido_imagen":"mc.png","votos":11982,"partido_siglas":"MC","color":"#EA622F","en_grafica":true,"en_tabla":true},{"partido_imagen":"mor.png","votos":12250,"partido_siglas":"MOR","color":"#B85756","en_grafica":true,"en_tabla":true},{"partido_imagen":"pes.png","votos":12907,"partido_siglas":"PES","color":"#E84445","en_grafica":true,"en_tabla":true},{"partido_imagen":"juan_bueno.png","votos":11840,"partido_siglas":"JUAN BUENO TORIO","color":"#97AB9F","en_grafica":true,"en_tabla":true},{"partido_imagen":"cnr.png","votos":1280,"partido_siglas":"CNR","color":"#878A87","en_grafica":true,"en_tabla":true},{"partido_imagen":"nulos.png","votos":1114,"partido_siglas":"NULOS","color":"#EEB4BF","en_grafica":true,"en_tabla":true}],"total_votantes":86794,"total_sobrantes":3700,"votos_sacados_urna":4374},{"nombre":"07 MART\u00cdNEZ DE LA TORRE","total_actas":342,"actas_procesadas":335,"actas_correctas":301,"actas_digitalizadas":335,"actas_acopiadas":341,"total_de_votos":80480,"lista_nominal":176344,"participacion":51.707,"porcentaje_actas_procesadas":88.0116,"votos_por_partido":[{"partido_imagen":"Pan-Prd.png","votos":10938,"partido_siglas":"Pan Prd","color":"#1081C0","en_grafica":true,"en_tabla":false},{"partido_imagen":"Pri-Pv-Na-Ave-PC.png","votos":11931,"partido_siglas":"Pri Pvem NA AVE Cardenista","color":"#17A151","en_grafica":true,"en_tabla":false},{"partido_imagen":"pt.png","votos":11048,"partido_siglas":"PT","color":"#E93E41","en_grafica":true,"en_tabla":true},{"partido_imagen":"mc.png","votos":11425,"partido_siglas":"MC","color":"#EA622F","en_grafica":true,"en_tabla":true},{"partido_imagen":"mor.png","votos":10809,"partido_siglas":"MOR","color":"#B85756","en_grafica":true,"en_tabla":true},{"partido_imagen":"pes.png","votos":11235,"partido_siglas":"PES","color":"#E84445","en_grafica":true,"en_tabla":true},{"partido_imagen":"juan_bueno.png","votos":11031,"partido_siglas":"JUAN BUENO TORIO","color":"#97AB9F","en_grafica":true,"en_tabla":true},{"partido_imagen":"cnr.png","votos":1138,"partido_siglas":"CNR","color":"#878A87","en_grafica":true,"en_tabla":true},{"partido_imagen":"nulos.png","votos":1131,"partido_siglas":"NULOS","color":"#EEB4BF","en_grafica":true,"en_tabla":true}],"total_votantes":8130,"total_sobrantes":3313,"votos_sacados_urna":60636},{"nombre":"08 MISANTLA","total_actas":380,"actas_procesadas":379,"actas_correctas":341,"actas_digitalizadas":379,"actas_acopiadas":380,"total_de_votos":85526,"lista_nominal":185638,"participacion":51.6832,"porcentaje_actas_procesadas":89.7368,"votos_por_partido":[{"partido_imagen":"Pan-Prd.png","votos":12005,"partido_siglas":"Pan Prd","color":"#1081C0","en_grafica":true,"en_tabla":false},{"partido_imagen":"Pri-Pv-Na-Ave-PC.png","votos":12660,"partido_siglas":"Pri Pvem NA AVE Cardenista","color":"#17A151","en_grafica":true,"en_tabla":false},{"partido_imagen":"pt.png","votos":10905,"partido_siglas":"PT","color":"#E93E41","en_grafica":true,"en_tabla":true},{"partido_imagen":"mc.png","votos":11429,"partido_siglas":"MC","color":"#EA622F","en_grafica":true,"en_tabla":true},{"partido_imagen":"mor.png","votos":11942,"partido_siglas":"MOR","color":"#B85756","en_grafica":true,"en_tabla":true},{"partido_imagen":"pes.png","votos":12113,"partido_siglas":"PES","color":"#E84445","en_grafica":true,"en_tabla":true},{"partido_imagen":"juan_bueno.png","votos":12351,"partido_siglas":"JUAN BUENO TORIO","color":"#97AB9F","en_grafica":true,"en_tabla":true},{"partido_imagen":"cnr.png","votos":1185,"partido_siglas":"CNR","color":"#878A87","en_grafica":true,"en_tabla":true},{"partido_imagen":"nulos.png","votos":1176,"partido_siglas":"NULOS","color":"#EEB4BF","en_grafica":true,"en_tabla":true}],"total_votantes":2178,"total_sobrantes":2188,"votos_sacados_urna":87723},{"nombre":"09 PEROTE","total_actas":317,"actas_procesadas":314,"actas_correctas":309,"actas_digitalizadas":311,"actas_acopiadas":317,"total_de_votos":86772,"lista_nominal":168267,"participacion":52.8266,"porcentaje_actas_procesadas":97.4763,"votos_por_partido":[{"partido_imagen":"Pan-Prd.png","votos":13917,"partido_siglas":"Pan Prd","color":"#1081C0","en_grafica":true,"en_tabla":false},{"partido_imagen":"Pri-Pv-Na-Ave-PC.png","votos":13867,"partido_siglas":"Pri Pvem NA AVE Cardenista","color":"#17A151","en_grafica":true,"en_tabla":false},{"partido_imagen":"pt.png","votos":10595,"partido_siglas":"PT","color":"#E93E41","en_grafica":true,"en_tabla":true},{"partido_imagen":"mc.png","votos":10334,"partido_siglas":"MC","color":"#EA622F","en_grafica":true,"en_tabla":true},{"partido_imagen":"mor.png","votos":9220,"partido_siglas":"MOR","color":"#B85756","en_grafica":true,"en_tabla":true},{"partido_imagen":"pes.png","votos":13529,"partido_siglas":"PES","color":"#E84445","en_grafica":true,"en_tabla":true},{"partido_imagen":"juan_bueno.png","votos":12732,"partido_siglas":"JUAN BUENO TORIO","color":"#97AB9F","en_grafica":true,"en_tabla":true},{"partido_imagen":"cnr.png","votos":1235,"partido_siglas":"CNR","color":"#878A87","en_grafica":true,"en_tabla":true},{"partido_imagen":"nulos.png","votos":1343,"partido_siglas":"NULOS","color":"#EEB4BF","en_grafica":true,"en_tabla":true}],"total_votantes":3434,"total_sobrantes":2488,"votos_sacados_urna":85857},{"nombre":"10 XALAPA","total_actas":304,"actas_procesadas":301,"actas_correctas":286,"actas_digitalizadas":290,"actas_acopiadas":303,"total_de_votos":87548,"lista_nominal":177680,"participacion":52.1488,"porcentaje_actas_procesadas":94.0789,"votos_por_partido":[{"partido_imagen":"Pan-Prd.png","votos":13147,"partido_siglas":"Pan Prd","color":"#1081C0","en_grafica":true,"en_tabla":false},{"partido_imagen":"Pri-Pv-Na-Ave-PC.png","votos":13256,"partido_siglas":"Pri Pvem NA AVE Cardenista","color":"#17A151","en_grafica":true,"en_tabla":false},{"partido_imagen":"pt.png","votos":11287,"partido_siglas":"PT","color":"#E93E41","en_grafica":true,"en_tabla":true},{"partido_imagen":"mc.png","votos":11700,"partido_siglas":"MC","color":"#EA622F","en_grafica":true,"en_tabla":true},{"partido_imagen":"mor.png","votos":11316,"partido_siglas":"MOR","color":"#B85756","en_grafica":true,"en_tabla":true},{"partido_imagen":"pes.png","votos":12774,"partido_siglas":"PES","color":"#E84445","en_grafica":true,"en_tabla":true},{"partido_imagen":"juan_bueno.png","votos":11677,"partido_siglas":"JUAN BUENO TORIO","color":"#97AB9F","en_grafica":true,"en_tabla":true},{"partido_imagen":"cnr.png","votos":1178,"partido_siglas":"CNR","color":"#878A87","en_grafica":true,"en_tabla":true},{"partido_imagen":"nulos.png","votos":1213,"partido_siglas":"NULOS","color":"#EEB4BF","en_grafica":true,"en_tabla":true}],"total_votantes":34924,"total_sobrantes":10551,"votos_sacados_urna":61713},{"nombre":"11 XALAPA","total_actas":314,"actas_procesadas":309,"actas_correctas":309,"actas_digitalizadas":309,"actas_acopiadas":314,"total_de_votos":92827,"lista_nominal":183827,"participacion":51.3409,"porcentaje_actas_procesadas":98.4076,"votos_por_partido":[{"partido_imagen":"Pan-Prd.png","votos":14845,"partido_siglas":"Pan Prd","color":"#1081C0","en_grafica":true,"en_tabla":false},{"partido_imagen":"Pri-Pv-Na-Ave-PC.png","votos":14191,"partido_siglas":"Pri Pvem NA AVE Cardenista","color":"#17A151","en_grafica":true,"en_tabla":false},{"partido_imagen":"pt.png","votos":12052,"partido_siglas":"PT","color":"#E93E41","en_grafica":true,"en_tabla":true},{"partido_imagen":"mc.png","votos":11062,"partido_siglas":"MC","color":"#EA622F","en_grafica":true,"en_tabla":true},{"partido_imagen":"mor.png","votos":11359,"partido_siglas":"MOR","color":"#B85756","en_grafica":true,"en_tabla":true},{"partido_imagen":"pes.png","votos":14084,"partido_siglas":"PES","color":"#E84445","en_grafica":true,"en_tabla":true},{"partido_imagen":"juan_bueno.png","votos":12454,"partido_siglas":"JUAN BUENO TORIO","color":"#97AB9F","en_grafica":true,"en_tabla":true},{"partido_imagen":"cnr.png","votos":1385,"partido_siglas":"CNR","color":"#878A87","en_grafica":true,"en_tabla":true},{"partido_imagen":"nulos.png","votos":1395,"partido_siglas":"NULOS","color":"#EEB4BF","en_grafica":true,"en_tabla":true}],"total_votantes":2386,"total_sobrantes":2761,"votos_sacados_urna":92862},{"nombre":"12 COATEPEC","total_actas":309,"actas_procesadas":308,"actas_correctas":307,"actas_digitalizadas":308,"actas_acopiadas":309,"total_de_votos":89924,"lista_nominal":175236,"participacion":51.6584,"porcentaje_actas_procesadas":99.3527,"votos_por_partido":[{"partido_imagen":"Pan-Prd.png","votos":13038,"partido_siglas":"Pan Prd","color":"#1081C0","en_grafica":true,"en_tabla":false},{"partido_imagen":"Pri-Pv-Na-Ave-PC.png","votos":13400,"partido_siglas":"Pri Pvem NA AVE Cardenista","color":"#17A151","en_grafica":true,"en_tabla":false},{"partido_imagen":"pt.png","votos":11940,"partido_siglas":"PT","color":"#E93E41","en_grafica":true,"en_tabla":true},{"partido_imagen":"mc.png","votos":12113,"partido_siglas":"MC","color":"#EA622F","en_grafica":true,"en_tabla":true},{"partido_imagen":"mor.png","votos":12136,"partido_siglas":"MOR","color":"#B85756","en_grafica":true,"en_tabla":true},{"partido_imagen":"pes.png","votos":12536,"partido_siglas":"PES","color":"#E84445","en_grafica":true,"en_tabla":true},{"partido_imagen":"juan_bueno.png","votos":12159,"partido_siglas":"JUAN BUENO TORIO","color":"#97AB9F","en_grafica":true,"en_tabla":true},{"partido_imagen":"cnr.png","votos":1245,"partido_siglas":"CNR","color":"#878A87","en_grafica":true,"en_tabla":true},{"partido_imagen":"nulos.png","votos":1357,"partido_siglas":"NULOS","color":"#EEB4BF","en_grafica":true,"en_tabla":true}],"total_votantes":91692,"total_sobrantes":2604,"votos_sacados_urna":91071},{"nombre":"13 EMILIANO ZAPATA","total_actas":350,"actas_procesadas":346,"actas_correctas":346,"actas_digitalizadas":346,"actas_acopiadas":350,"total_de_votos":93255,"lista_nominal":182984,"participacion":51.5616,"porcentaje_actas_procesadas":98.8571,"votos_por_partido":[{"partido_imagen":"Pan-Prd.png","votos":14725,"partido_siglas":"Pan Prd","color":"#1081C0","en_grafica":true,"en_tabla":false},{"partido_imagen":"Pri-Pv-Na-Ave-PC.png","votos":14479,"partido_siglas":"Pri Pvem NA AVE Cardenista","color":"#17A151","en_grafica":true,"en_tabla":false},{"partido_imagen":"pt.png","votos":11971,"partido_siglas":"PT","color":"#E93E41","en_grafica":true,"en_tabla":true},{"partido_imagen":"mc.png","votos":11150,"partido_siglas":"MC","color":"#EA622F","en_grafica":true,"en_tabla":true},{"partido_imagen":"mor.png","votos":11709,"partido_siglas":"MOR","color":"#B85756","en_grafica":true,"en_tabla":true},{"partido_imagen":"pes.png","votos":14165,"partido_siglas":"PES","color":"#E84445","en_grafica":true,"en_tabla":true},{"partido_imagen":"juan_bueno.png","votos":12294,"partido_siglas":"JUAN BUENO TORIO","color":"#97AB9F","en_grafica":true,"en_tabla":true},{"partido_imagen":"cnr.png","votos":1438,"partido_siglas":"CNR","color":"#878A87","en_grafica":true,"en_tabla":true},{"partido_imagen":"nulos.png","votos":1324,"partido_siglas":"NULOS","color":"#EEB4BF","en_grafica":true,"en_tabla":true}],"total_votantes":340,"total_sobrantes":496,"votos_sacados_urna":344},{"nombre":"14 VERACRUZ","total_actas":379,"actas_procesadas":379,"actas_correctas":324,"actas_digitalizadas":379,"actas_acopiadas":379,"total_de_votos":95744,"lista_nominal":217523,"participacion":51.4694,"porcentaje_actas_procesadas":85.4881,"votos_por_partido":[{"partido_imagen":"Pan-Prd.png","votos":12651,"partido_siglas":"Pan Prd","color":"#1081C0","en_grafica":true,"en_tabla":false},{"partido_imagen":"Pri-Pv-Na-Ave-PC.png","votos":14248,"partido_siglas":"Pri Pvem NA AVE Cardenista","color":"#17A151","en_grafica":true,"en_tabla":false},{"partido_imagen":"pt.png","votos":12766,"partido_siglas":"PT","color":"#E93E41","en_grafica":true,"en_tabla":true},{"partido_imagen":"mc.png","votos":12420,"partido_siglas":"MC","color":"#EA622F","en_grafica":true,"en_tabla":true},{"partido_imagen":"mor.png","votos":13467,"partido_siglas":"MOR","color":"#B85756","en_grafica":true,"en_tabla":true},{"partido_imagen":"pes.png","votos":13073,"partido_siglas":"PES","color":"#E84445","en_grafica":true,"en_tabla":true},{"partido_imagen":"juan_bueno.png","votos":14268,"partido_siglas":"JUAN BUENO TORIO","color":"#97AB9F","en_grafica":true,"en_tabla":true},{"partido_imagen":"cnr.png","votos":1379,"partido_siglas":"CNR","color":"#878A87","en_grafica":true,"en_tabla":true},{"partido_imagen":"nulos.png","votos":1472,"partido_siglas":"NULOS","color":"#EEB4BF","en_grafica":true,"en_tabla":true}],"total_votantes":73004,"total_sobrantes":2168,"votos_sacados_urna":2839},{"nombre":"15 VERACRUZ","total_actas":399,"actas_procesadas":395,"actas_correctas":395,"actas_digitalizadas":395,"actas_acopiadas":397,"total_de_votos":119445,"lista_nominal":227222,"participacion":53.1502,"porcentaje_actas_procesadas":98.9974,"votos_por_partido":[{"partido_imagen":"Pan-Prd.png","votos":16092,"partido_siglas":"Pan Prd","color":"#1081C0","en_grafica":true,"en_tabla":false},{"partido_imagen":"Pri-Pv-Na-Ave-PC.png","votos":17356,"partido_siglas":"Pri Pvem NA AVE Cardenista","color":"#17A151","en_grafica":true,"en_tabla":false},{"partido_imagen":"pt.png","votos":16144,"partido_siglas":"PT","color":"#E93E41","en_grafica":true,"en_tabla":true},{"partido_imagen":"mc.png","votos":16024,"partido_siglas":"MC","color":"#EA622F","en_grafica":true,"en_tabla":true},{"partido_imagen":"mor.png","votos":16363,"partido_siglas":"MOR","color":"#B85756","en_grafica":true,"en_tabla":true},{"partido_imagen":"pes.png","votos":16894,"partido_siglas":"PES","color":"#E84445","en_grafica":true,"en_tabla":true},{"partido_imagen":"juan_bueno.png","votos":16301,"partido_siglas":"JUAN BUENO TORIO","color":"#97AB9F","en_grafica":true,"en_tabla":true},{"partido_imagen":"cnr.png","votos":1581,"partido_siglas":"CNR","color":"#878A87","en_grafica":true,"en_tabla":true},{"partido_imagen":"nulos.png","votos":1683,"partido_siglas":"NULOS","color":"#EEB4BF","en_grafica":true,"en_tabla":true}],"total_votantes":119379,"total_sobrantes":1578,"votos_sacados_urna":0},{"nombre":"16 BOCA DEL R\u00cdO","total_actas":378,"actas_procesadas":370,"actas_correctas":334,"actas_digitalizadas":370,"actas_acopiadas":373,"total_de_votos":96587,"lista_nominal":207755,"participacion":52.3589,"porcentaje_actas_procesadas":88.3597,"votos_por_partido":[{"partido_imagen":"Pan-Prd.png","votos":13302,"partido_siglas":"Pan Prd","color":"#1081C0","en_grafica":true,"en_tabla":false},{"partido_imagen":"Pri-Pv-Na-Ave-PC.png","votos":14120,"partido_siglas":"Pri Pvem NA AVE Cardenista","color":"#17A151","en_grafica":true,"en_tabla":false},{"partido_imagen":"pt.png","votos":13074,"partido_siglas":"PT","color":"#E93E41","en_grafica":true,"en_tabla":true},{"partido_imagen":"mc.png","votos":13517,"partido_siglas":"MC","color":"#EA622F","en_grafica":true,"en_tabla":true},{"partido_imagen":"mor.png","votos":13290,"partido_siglas":"MOR","color":"#B85756","en_grafica":true,"en_tabla":true},{"partido_imagen":"pes.png","votos":13327,"partido_siglas":"PES","color":"#E84445","en_grafica":true,"en_tabla":true},{"partido_imagen":"juan_bueno.png","votos":13335,"partido_siglas":"JUAN BUENO TORIO","color":"#97AB9F","en_grafica":true,"en_tabla":true},{"partido_imagen":"cnr.png","votos":1243,"partido_siglas":"CNR","color":"#878A87","en_grafica":true,"en_tabla":true},{"partido_imagen":"nulos.png","votos":1379,"partido_siglas":"NULOS","color":"#EEB4BF","en_grafica":true,"en_tabla":true}],"total_votantes":77867,"total_sobrantes":3403,"votos_sacados_urna":2429},{"nombre":"17 MEDELL\u00cdN","total_actas":339,"actas_procesadas":337,"actas_correctas":279,"actas_digitalizadas":335,"actas_acopiadas":339,"total_de_votos":78097,"lista_nominal":185371,"participacion":51.3914,"porcentaje_actas_procesadas":82.3008,"votos_por_partido":[{"partido_imagen":"Pan-Prd.png","votos":10742,"partido_siglas":"Pan Prd","color":"#1081C0","en_grafica":true,"en_tabla":false},{"partido_imagen":"Pri-Pv-Na-Ave-PC.png","votos":11460,"partido_siglas":"Pri Pvem NA AVE Cardenista","color":"#17A151","en_grafica":true,"en_tabla":false},{"partido_imagen":"pt.png","votos":10912,"partido_siglas":"PT","color":"#E93E41","en_grafica":true,"en_tabla":true},{"partido_imagen":"mc.png","votos":10694,"partido_siglas":"MC","color":"#EA622F","en_grafica":true,"en_tabla":true},{"partido_imagen":"mor.png","votos":10615,"partido_siglas":"MOR","color":"#B85756","en_grafica":true,"en_tabla":true},{"partido_imagen":"pes.png","votos":10488,"partido_siglas":"PES","color":"#E84445","en_grafica":true,"en_tabla":true},{"partido_imagen":"juan_bueno.png","votos":10973,"partido_siglas":"JUAN BUENO TORIO","color":"#97AB9F","en_grafica":true,"en_tabla":true},{"partido_imagen":"cnr.png","votos":1144,"partido_siglas":"CNR","color":"#878A87","en_grafica":true,"en_tabla":true},{"partido_imagen":"nulos.png","votos":1069,"partido_siglas":"NULOS","color":"#EEB4BF","en_grafica":true,"en_tabla":true}],"total_votantes":78548,"total_sobrantes":304,"votos_sacados_urna":2},{"nombre":"18 HUATUSCO","total_actas":303,"actas_procesadas":299,"actas_correctas":268,"actas_digitalizadas":299,"actas_acopiadas":303,"total_de_votos":78735,"lista_nominal":172008,"participacion":51.722,"porcentaje_actas_procesadas":88.4488,"votos_por_partido":[{"partido_imagen":"Pan-Prd.png","votos":10854,"partido_siglas":"Pan Prd","color":"#1081C0","en_grafica":true,"en_tabla":false},{"partido_imagen":"Pri-Pv-Na-Ave-PC.png","votos":11334,"partido_siglas":"Pri Pvem NA AVE Cardenista","color":"#17A151","en_grafica":true,"en_tabla":false},{"partido_imagen":"pt.png","votos":11012,"partido_siglas":"PT","color":"#E93E41","en_grafica":true,"en_tabla":true},{"partido_imagen":"mc.png","votos":10994,"partido_siglas":"MC","color":"#EA622F","en_grafica":true,"en_tabla":true},{"partido_imagen":"mor.png","votos":10650,"partido_siglas":"MOR","color":"#B85756","en_grafica":true,"en_tabla":true},{"partido_imagen":"pes.png","votos":10591,"partido_siglas":"PES","color":"#E84445","en_grafica":true,"en_tabla":true},{"partido_imagen":"juan_bueno.png","votos":11216,"partido_siglas":"JUAN BUENO TORIO","color":"#97AB9F","en_grafica":true,"en_tabla":true},{"partido_imagen":"cnr.png","votos":1044,"partido_siglas":"CNR","color":"#878A87","en_grafica":true,"en_tabla":true},{"partido_imagen":"nulos.png","votos":1040,"partido_siglas":"NULOS","color":"#EEB4BF","en_grafica":true,"en_tabla":true}],"total_votantes":691,"total_sobrantes":1503,"votos_sacados_urna":691},{"nombre":"19 C\u00d3RDOBA","total_actas":348,"actas_procesadas":348,"actas_correctas":314,"actas_digitalizadas":332,"actas_acopiadas":348,"total_de_votos":89475,"lista_nominal":194588,"participacion":51.2025,"porcentaje_actas_procesadas":90.2298,"votos_por_partido":[{"partido_imagen":"Pan-Prd.png","votos":12196,"partido_siglas":"Pan Prd","color":"#1081C0","en_grafica":true,"en_tabla":false},{"partido_imagen":"Pri-Pv-Na-Ave-PC.png","votos":13226,"partido_siglas":"Pri Pvem NA AVE Cardenista","color":"#17A151","en_grafica":true,"en_tabla":false},{"partido_imagen":"pt.png","votos":12880,"partido_siglas":"PT","color":"#E93E41","en_grafica":true,"en_tabla":true},{"partido_imagen":"mc.png","votos":12753,"partido_siglas":"MC","color":"#EA622F","en_grafica":true,"en_tabla":true},{"partido_imagen":"mor.png","votos":12274,"partido_siglas":"MOR","color":"#B85756","en_grafica":true,"en_tabla":true},{"partido_imagen":"pes.png","votos":11703,"partido_siglas":"PES","color":"#E84445","en_grafica":true,"en_tabla":true},{"partido_imagen":"juan_bueno.png","votos":12070,"partido_siglas":"JUAN BUENO TORIO","color":"#97AB9F","en_grafica":true,"en_tabla":true},{"partido_imagen":"cnr.png","votos":1214,"partido_siglas":"CNR","color":"#878A87","en_grafica":true,"en_tabla":true},{"partido_imagen":"nulos.png","votos":1159,"partido_siglas":"NULOS","color":"#EEB4BF","en_grafica":true,"en_tabla":true}],"total_votantes":5993,"total_sobrantes":2230,"votos_sacados_urna":88717},{"nombre":"20 ORIZABA","total_actas":360,"actas_procesadas":359,"actas_correctas":313,"actas_digitalizadas":358,"actas_acopiadas":360,"total_de_votos":92023,"lista_nominal":200593,"participacion":52.7694,"porcentaje_actas_procesadas":86.9444,"votos_por_partido":[{"partido_imagen":"Pan-Prd.png","votos":12656,"partido_siglas":"Pan Prd","color":"#1081C0","en_grafica":true,"en_tabla":false},{"partido_imagen":"Pri-Pv-Na-Ave-PC.png","votos":13608,"partido_siglas":"Pri Pvem NA AVE Cardenista","color":"#17A151","en_grafica":true,"en_tabla":false},{"partido_imagen":"pt.png","votos":12852,"partido_siglas":"PT","color":"#E93E41","en_grafica":true,"en_tabla":true},{"partido_imagen":"mc.png","votos":12072,"partido_siglas":"MC","color":"#EA622F","en_grafica":true,"en_tabla":true},{"partido_imagen":"mor.png","votos":12865,"partido_siglas":"MOR","color":"#B85756","en_grafica":true,"en_tabla":true},{"partido_imagen":"pes.png","votos":12341,"partido_siglas":"PES","color":"#E84445","en_grafica":true,"en_tabla":true},{"partido_imagen":"juan_bueno.png","votos":12991,"partido_siglas":"JUAN BUENO TORIO","color":"#97AB9F","en_grafica":true,"en_tabla":true},{"partido_imagen":"cnr.png","votos":1334,"partido_siglas":"CNR","color":"#878A87","en_grafica":true,"en_tabla":true},{"partido_imagen":"nulos.png","votos":1304,"partido_siglas":"NULOS","color":"#EEB4BF","en_grafica":true,"en_tabla":true}],"total_votantes":1038,"total_sobrantes":156,"votos_sacados_urna":1349},{"nombre":"21 CAMERINO Z. MENDOZA","total_actas":294,"actas_procesadas":294,"actas_correctas":257,"actas_digitalizadas":292,"actas_acopiadas":294,"total_de_votos":77424,"lista_nominal":169017,"participacion":52.2778,"porcentaje_actas_procesadas":87.4149,"votos_por_partido":[{"partido_imagen":"Pan-Prd.png","votos":11568,"partido_siglas":"Pan Prd","color":"#1081C0","en_grafica":true,"en_tabla":false},{"partido_imagen":"Pri-Pv-Na-Ave-PC.png","votos":12679,"partido_siglas":"Pri Pvem NA AVE Cardenista","color":"#17A151","en_grafica":true,"en_tabla":false},{"partido_imagen":"pt.png","votos":10632,"partido_siglas":"PT","color":"#E93E41","en_grafica":true,"en_tabla":true},{"partido_imagen":"mc.png","votos":10545,"partido_siglas":"MC","color":"#EA622F","en_grafica":true,"en_tabla":true},{"partido_imagen":"mor.png","votos":10383,"partido_siglas":"MOR","color":"#B85756","en_grafica":true,"en_tabla":true},{"partido_imagen":"pes.png","votos":10270,"partido_siglas":"PES","color":"#E84445","en_grafica":true,"en_tabla":true},{"partido_imagen":"juan_bueno.png","votos":9381,"partido_siglas":"JUAN BUENO TORIO","color":"#97AB9F","en_grafica":true,"en_tabla":true},{"partido_imagen":"cnr.png","votos":969,"partido_siglas":"CNR","color":"#878A87","en_grafica":true,"en_tabla":true},{"partido_imagen":"nulos.png","votos":997,"partido_siglas":"NULOS","color":"#EEB4BF","en_grafica":true,"en_tabla":true}],"total_votantes":2584,"total_sobrantes":1238,"votos_sacados_urna":25095},{"nombre":"22 ZONGOLICA","total_actas":292,"actas_procesadas":279,"actas_correctas":242,"actas_digitalizadas":249,"actas_acopiadas":281,"total_de_votos":67669,"lista_nominal":162438,"participacion":50.4777,"porcentaje_actas_procesadas":82.8767,"votos_por_partido":[{"partido_imagen":"Pan-Prd.png","votos":9692,"partido_siglas":"Pan Prd","color":"#1081C0","en_grafica":true,"en_tabla":false},{"partido_imagen":"Pri-Pv-Na-Ave-PC.png","votos":10071,"partido_siglas":"Pri Pvem NA AVE Cardenista","color":"#17A151","en_grafica":true,"en_tabla":false},{"partido_imagen":"pt.png","votos":9035,"partido_siglas":"PT","color":"#E93E41","en_grafica":true,"en_tabla":true},{"partido_imagen":"mc.png","votos":8816,"partido_siglas":"MC","color":"#EA622F","en_grafica":true,"en_tabla":true},{"partido_imagen":"mor.png","votos":9869,"partido_siglas":"MOR","color":"#B85756","en_grafica":true,"en_tabla":true},{"partido_imagen":"pes.png","votos":8801,"partido_siglas":"PES","color":"#E84445","en_grafica":true,"en_tabla":true},{"partido_imagen":"juan_bueno.png","votos":9428,"partido_siglas":"JUAN BUENO TORIO","color":"#97AB9F","en_grafica":true,"en_tabla":true},{"partido_imagen":"cnr.png","votos":991,"partido_siglas":"CNR","color":"#878A87","en_grafica":true,"en_tabla":true},{"partido_imagen":"nulos.png","votos":966,"partido_siglas":"NULOS","color":"#EEB4BF","en_grafica":true,"en_tabla":true}],"total_votantes":66921,"total_sobrantes":1310,"votos_sacados_urna":363},{"nombre":"23 COSAMALOAPAN","total_actas":386,"actas_procesadas":385,"actas_correctas":320,"actas_digitalizadas":385,"actas_acopiadas":386,"total_de_votos":86156,"lista_nominal":199506,"participacion":52.5293,"porcentaje_actas_procesadas":82.9015,"votos_por_partido":[{"partido_imagen":"Pan-Prd.png","votos":12257,"partido_siglas":"Pan Prd","color":"#1081C0","en_grafica":true,"en_tabla":false},{"partido_imagen":"Pri-Pv-Na-Ave-PC.png","votos":12847,"partido_siglas":"Pri Pvem NA AVE Cardenista","color":"#17A151","en_grafica":true,"en_tabla":false},{"partido_imagen":"pt.png","votos":11659,"partido_siglas":"PT","color":"#E93E41","en_grafica":true,"en_tabla":true},{"partido_imagen":"mc.png","votos":12315,"partido_siglas":"MC","color":"#EA622F","en_grafica":true,"en_tabla":true},{"partido_imagen":"mor.png","votos":11481,"partido_siglas":"MOR","color":"#B85756","en_grafica":true,"en_tabla":true},{"partido_imagen":"pes.png","votos":11854,"partido_siglas":"PES","color":"#E84445","en_grafica":true,"en_tabla":true},{"partido_imagen":"juan_bueno.png","votos":12006,"partido_siglas":"JUAN BUENO TORIO","color":"#97AB9F","en_grafica":true,"en_tabla":true},{"partido_imagen":"cnr.png","votos":1214,"partido_siglas":"CNR","color":"#878A87","en_grafica":true,"en_tabla":true},{"partido_imagen":"nulos.png","votos":1241,"partido_siglas":"NULOS","color":"#EEB4BF","en_grafica":true,"en_tabla":true}],"total_votantes":70937,"total_sobrantes":2005,"votos_sacados_urna":17930},{"nombre":"24 SANTIAGO TUXTLA","total_actas":360,"actas_procesadas":357,"actas_correctas":332,"actas_digitalizadas":357,"actas_acopiadas":360,"total_de_votos":93079,"lista_nominal":194287,"participacion":51.605,"porcentaje_actas_procesadas":92.2222,"votos_por_partido":[{"partido_imagen":"Pan-Prd.png","votos":13005,"partido_siglas":"Pan Prd","color":"#1081C0","en_grafica":true,"en_tabla":false},{"partido_imagen":"Pri-Pv-Na-Ave-PC.png","votos":13913,"partido_siglas":"Pri Pvem NA AVE Cardenista","color":"#17A151","en_grafica":true,"en_tabla":false},{"partido_imagen":"pt.png","votos":13076,"partido_siglas":"PT","color":"#E93E41","en_grafica":true,"en_tabla":true},{"partido_imagen":"mc.png","votos":12957,"partido_siglas":"MC","color":"#EA622F","en_grafica":true,"en_tabla":true},{"partido_imagen":"mor.png","votos":13117,"partido_siglas":"MOR","color":"#B85756","en_grafica":true,"en_tabla":true},{"partido_imagen":"pes.png","votos":11867,"partido_siglas":"PES","color":"#E84445","en_grafica":true,"en_tabla":true},{"partido_imagen":"juan_bueno.png","votos":12814,"partido_siglas":"JUAN BUENO TORIO","color":"#97AB9F","en_grafica":true,"en_tabla":true},{"partido_imagen":"cnr.png","votos":1326,"partido_siglas":"CNR","color":"#878A87","en_grafica":true,"en_tabla":true},{"partido_imagen":"nulos.png","votos":1344,"partido_siglas":"NULOS","color":"#EEB4BF","en_grafica":true,"en_tabla":true}],"total_votantes":34465,"total_sobrantes":299,"votos_sacados_urna":191},{"nombre":"25 SAN ANDR\u00c9S TUXTLA","total_actas":313,"actas_procesadas":308,"actas_correctas":276,"actas_digitalizadas":308,"actas_acopiadas":309,"total_de_votos":80732,"lista_nominal":178466,"participacion":51.5856,"porcentaje_actas_procesadas":88.1789,"votos_por_partido":[{"partido_imagen":"Pan-Prd.png","votos":11170,"partido_siglas":"Pan Prd","color":"#1081C0","en_grafica":true,"en_tabla":false},{"partido_imagen":"Pri-Pv-Na-Ave-PC.png","votos":12367,"partido_siglas":"Pri Pvem NA AVE Cardenista","color":"#17A151","en_grafica":true,"en_tabla":false},{"partido_imagen":"pt.png","votos":11203,"partido_siglas":"PT","color":"#E93E41","en_grafica":true,"en_tabla":true},{"partido_imagen":"mc.png","votos":11210,"partido_siglas":"MC","color":"#EA622F","en_grafica":true,"en_tabla":true},{"partido_imagen":"mor.png","votos":10458,"partido_siglas":"MOR","color":"#B85756","en_grafica":true,"en_tabla":true},{"partido_imagen":"pes.png","votos":11409,"partido_siglas":"PES","color":"#E84445","en_grafica":true,"en_tabla":true},{"partido_imagen":"juan_bueno.png","votos":10927,"partido_siglas":"JUAN BUENO TORIO","color":"#97AB9F","en_grafica":true,"en_tabla":true},{"partido_imagen":"cnr.png","votos":1091,"partido_siglas":"CNR","color":"#878A87","en_grafica":true,"en_tabla":true},{"partido_imagen":"nulos.png","votos":1114,"partido_siglas":"NULOS","color":"#EEB4BF","en_grafica":true,"en_tabla":true}],"total_votantes":71494,"total_sobrantes":1938,"votos_sacados_urna":2613},{"nombre":"26 COSOLEACAQUE","total_actas":369,"actas_procesadas":368,"actas_correctas":330,"actas_digitalizadas":368,"actas_acopiadas":369,"total_de_votos":90156,"lista_nominal":204741,"participacion":49.3356,"porcentaje_actas_procesadas":89.4308,"votos_por_partido":[{"partido_imagen":"Pan-Prd.png","votos":12797,"partido_siglas":"Pan Prd","color":"#1081C0","en_grafica":true,"en_tabla":false},{"partido_imagen":"Pri-Pv-Na-Ave-PC.png","votos":13597,"partido_siglas":"Pri Pvem NA AVE Cardenista","color":"#17A151","en_grafica":true,"en_tabla":false},{"partido_imagen":"pt.png","votos":12565,"partido_siglas":"PT","color":"#E93E41","en_grafica":true,"en_tabla":true},{"partido_imagen":"mc.png","votos":12396,"partido_siglas":"MC","color":"#EA622F","en_grafica":true,"en_tabla":true},{"partido_imagen":"mor.png","votos":11966,"partido_siglas":"MOR","color":"#B85756","en_grafica":true,"en_tabla":true},{"partido_imagen":"pes.png","votos":12392,"partido_siglas":"PES","color":"#E84445","en_grafica":true,"en_tabla":true},{"partido_imagen":"juan_bueno.png","votos":11812,"partido_siglas":"JUAN BUENO TORIO","color":"#97AB9F","en_grafica":true,"en_tabla":true},{"partido_imagen":"cnr.png","votos":1321,"partido_siglas":"CNR","color":"#878A87","en_grafica":true,"en_tabla":true},{"partido_imagen":"nulos.png","votos":1310,"partido_siglas":"NULOS","color":"#EEB4BF","en_grafica":true,"en_tabla":true}],"total_votantes":92598,"total_sobrantes":2056,"votos_sacados_urna":1351},{"nombre":"27 ACAYUCAN","total_actas":329,"actas_procesadas":328,"actas_correctas":311,"actas_digitalizadas":328,"actas_acopiadas":329,"total_de_votos":88290,"lista_nominal":181385,"participacion":51.4642,"porcentaje_actas_procesadas":94.5288,"votos_por_partido":[{"partido_imagen":"Pan-Prd.png","votos":12527,"partido_siglas":"Pan Prd","color":"#1081C0","en_grafica":true,"en_tabla":false},{"partido_imagen":"Pri-Pv-Na-Ave-PC.png","votos":13561,"partido_siglas":"Pri Pvem NA AVE Cardenista","color":"#17A151","en_grafica":true,"en_tabla":false},{"partido_imagen":"pt.png","votos":12389,"partido_siglas":"PT","color":"#E93E41","en_grafica":true,"en_tabla":true},{"partido_imagen":"mc.png","votos":12127,"partido_siglas":"MC","color":"#EA622F","en_grafica":true,"en_tabla":true},{"partido_imagen":"mor.png","votos":12339,"partido_siglas":"MOR","color":"#B85756","en_grafica":true,"en_tabla":true},{"partido_imagen":"pes.png","votos":11639,"partido_siglas":"PES","color":"#E84445","en_grafica":true,"en_tabla":true},{"partido_imagen":"juan_bueno.png","votos":11148,"partido_siglas":"JUAN BUENO TORIO","color":"#97AB9F","en_grafica":true,"en_tabla":true},{"partido_imagen":"cnr.png","votos":1449,"partido_siglas":"CNR","color":"#878A87","en_grafica":true,"en_tabla":true},{"partido_imagen":"nulos.png","votos":1111,"partido_siglas":"NULOS","color":"#EEB4BF","en_grafica":true,"en_tabla":true}],"total_votantes":908,"total_sobrantes":173,"votos_sacados_urna":766},{"nombre":"28 MINATITL\u00c1N","total_actas":341,"actas_procesadas":338,"actas_correctas":303,"actas_digitalizadas":338,"actas_acopiadas":340,"total_de_votos":78347,"lista_nominal":173581,"participacion":50.4254,"porcentaje_actas_procesadas":88.8563,"votos_por_partido":[{"partido_imagen":"Pan-Prd.png","votos":11000,"partido_siglas":"Pan Prd","color":"#1081C0","en_grafica":true,"en_tabla":false},{"partido_imagen":"Pri-Pv-Na-Ave-PC.png","votos":11709,"partido_siglas":"Pri Pvem NA AVE Cardenista","color":"#17A151","en_grafica":true,"en_tabla":false},{"partido_imagen":"pt.png","votos":10736,"partido_siglas":"PT","color":"#E93E41","en_grafica":true,"en_tabla":true},{"partido_imagen":"mc.png","votos":11011,"partido_siglas":"MC","color":"#EA622F","en_grafica":true,"en_tabla":true},{"partido_imagen":"mor.png","votos":11030,"partido_siglas":"MOR","color":"#B85756","en_grafica":true,"en_tabla":true},{"partido_imagen":"pes.png","votos":10164,"partido_siglas":"PES","color":"#E84445","en_grafica":true,"en_tabla":true},{"partido_imagen":"juan_bueno.png","votos":10481,"partido_siglas":"JUAN BUENO TORIO","color":"#97AB9F","en_grafica":true,"en_tabla":true},{"partido_imagen":"cnr.png","votos":1088,"partido_siglas":"CNR","color":"#878A87","en_grafica":true,"en_tabla":true},{"partido_imagen":"nulos.png","votos":1128,"partido_siglas":"NULOS","color":"#EEB4BF","en_grafica":true,"en_tabla":true}],"total_votantes":80451,"total_sobrantes":14,"votos_sacados_urna":914},{"nombre":"29 COATZACOALCOS","total_actas":353,"actas_procesadas":353,"actas_correctas":330,"actas_digitalizadas":353,"actas_acopiadas":353,"total_de_votos":95058,"lista_nominal":195052,"participacion":52.1628,"porcentaje_actas_procesadas":93.4844,"votos_por_partido":[{"partido_imagen":"Pan-Prd.png","votos":13539,"partido_siglas":"Pan Prd","color":"#1081C0","en_grafica":true,"en_tabla":false},{"partido_imagen":"Pri-Pv-Na-Ave-PC.png","votos":14099,"partido_siglas":"Pri Pvem NA AVE Cardenista","color":"#17A151","en_grafica":true,"en_tabla":false},{"partido_imagen":"pt.png","votos":14365,"partido_siglas":"PT","color":"#E93E41","en_grafica":true,"en_tabla":true},{"partido_imagen":"mc.png","votos":12570,"partido_siglas":"MC","color":"#EA622F","en_grafica":true,"en_tabla":true},{"partido_imagen":"mor.png","votos":12389,"partido_siglas":"MOR","color":"#B85756","en_grafica":true,"en_tabla":true},{"partido_imagen":"pes.png","votos":12324,"partido_siglas":"PES","color":"#E84445","en_grafica":true,"en_tabla":true},{"partido_imagen":"juan_bueno.png","votos":13084,"partido_siglas":"JUAN BUENO TORIO","color":"#97AB9F","en_grafica":true,"en_tabla":true},{"partido_imagen":"cnr.png","votos":1325,"partido_siglas":"CNR","color":"#878A87","en_grafica":true,"en_tabla":true},{"partido_imagen":"nulos.png","votos":1363,"partido_siglas":"NULOS","color":"#EEB4BF","en_grafica":true,"en_tabla":true}],"total_votantes":92545,"total_sobrantes":2523,"votos_sacados_urna":386},{"nombre":"30 COATZACOALCOS","total_actas":355,"actas_procesadas":351,"actas_correctas":327,"actas_digitalizadas":351,"actas_acopiadas":353,"total_de_votos":89974,"lista_nominal":185400,"participacion":53.0166,"porcentaje_actas_procesadas":92.1126,"votos_por_partido":[{"partido_imagen":"Pan-Prd.png","votos":12680,"partido_siglas":"Pan Prd","color":"#1081C0","en_grafica":true,"en_tabla":false},{"partido_imagen":"Pri-Pv-Na-Ave-PC.png","votos":13049,"partido_siglas":"Pri Pvem NA AVE Cardenista","color":"#17A151","en_grafica":true,"en_tabla":false},{"partido_imagen":"pt.png","votos":12204,"partido_siglas":"PT","color":"#E93E41","en_grafica":true,"en_tabla":true},{"partido_imagen":"mc.png","votos":12328,"partido_siglas":"MC","color":"#EA622F","en_grafica":true,"en_tabla":true},{"partido_imagen":"mor.png","votos":12076,"partido_siglas":"MOR","color":"#B85756","en_grafica":true,"en_tabla":true},{"partido_imagen":"pes.png","votos":11932,"partido_siglas":"PES","color":"#E84445","en_grafica":true,"en_tabla":true},{"partido_imagen":"juan_bueno.png","votos":12149,"partido_siglas":"JUAN BUENO TORIO","color":"#97AB9F","en_grafica":true,"en_tabla":true},{"partido_imagen":"cnr.png","votos":1301,"partido_siglas":"CNR","color":"#878A87","en_grafica":true,"en_tabla":true},{"partido_imagen":"nulos.png","votos":1250,"partido_siglas":"NULOS","color":"#EEB4BF","en_grafica":true,"en_tabla":true}],"total_votantes":89524,"total_sobrantes":1174,"votos_sacados_urna":1099}],"portada":{"titulo":"Elecci\u00f3n de Gobernador","avance_capturas":89.7514,"actas_totales":10421,"votos":2623248,"actas_capturadas":10327,"porcentaje_participacion":51.5312,"PorcentajeActasCapturadasGobernador":89.7514,"actas_correctas":9353,"actas_esperadas":10421,"candidatos":[{"nombre":"Candidato PAN","votos":372808,"imagen":"Pan-Prd.png","color":"#1081C0","porcentaje":14.211694814},{"nombre":"Candidato PRI","votos":378197,"imagen":"Pri-Pv-Na-Ave-PC.png","color":"#17A151","porcentaje":14.417127164},{"nombre":"Candidato PT","votos":359654,"imagen":"pt.png","color":"#E93E41","porcentaje":13.710255378},{"nombre":"Candidato MC","votos":357285,"imagen":"mc.png","color":"#EA622F","porcentaje":13.619947484},{"nombre":"Candidato Morena","votos":355155,"imagen":"mor.png","color":"#B85756","porcentaje":13.538750434},{"nombre":"Candidato Encuentro Social","votos":364865,"imagen":"pes.png","color":"#E84445","porcentaje":13.908902246},{"nombre":"Candidato Independiente","votos":361144,"imagen":"juan_bueno.png","color":"#97AB9F","porcentaje":13.767055192},{"nombre":"CNR","votos":37244,"imagen":"cnr.png","color":"#878A87","porcentaje":1.41976664},{"nombre":"Nulos","votos":36896,"imagen":"nulos.png","color":"#EEB4BF","porcentaje":1.406500643}],"lista_nominal_actas_computadas":5090599,"actas_digitalizadas":10205,"actas_acopiadas":10389,"actas_procesadas":10327,"total_votantes":1443900,"total_sobrantes":63032,"votos_sacados_urna":822485,"total_actas_procesadas_dg":20787,"total_actas_dg":20842,"total_actas_procesadas_d":10353,"total_actas_d":10421,"ActasConInconsistencia":974,"PorcentajeActasConInconsistenciaGobernador":9.3465,"AvanceCapturaTotal":99.7361,"PorcentajeActasPublicadas":99.0979,"TotalActasProcesadasGobernador":10327,"diputados":{"ListaNominalGlobalDiputados":5043828,"votos":2831664,"actas_acopiadas_diputados":10398,"PorcentajeActasAcopiadasGlobalDiputados":99.7792,"TotalActasProcesadasDiputados":10353,"PorcentajeActasPublicadasDiputados":99.3474,"actas_correctas_diputados":9264,"AvanceCapturaDiputados":88.897418673,"ActasConInconsistenciaDiputados":1089,"PorcentajeActasConInconsistenciaDiputados":10.45}},"extradata":{"hora_actualizacion":"2016-06-02 23:27:50","simulacro":50}}